LICENSE
MANIFEST.in
README.md
setup.py
interactive_components/__init__.py
interactive_components/_type_checker_decorator.py
interactive_components/color.py
interactive_components/config.py
interactive_components/output_block.py
interactive_components/title.py
interactive_components/utils.py
interactive_components.egg-info/PKG-INFO
interactive_components.egg-info/SOURCES.txt
interactive_components.egg-info/dependency_links.txt
interactive_components.egg-info/top_level.txt
interactive_components/editors/__init__.py
interactive_components/editors/sequential_editor.py
interactive_components/editors/static_editor.py
interactive_components/menus/__init__.py
interactive_components/menus/keyed_menu.py
interactive_components/menus/numeric_menu.py