Metadata-Version: 1.2
Name: interactive-components
Version: 1.0.0
Summary: A set of tools to build useful components for interactive python scripts
Home-page: UNKNOWN
Author: Adrià Sarquella Farrés
Author-email: adrisarquella@gmail.com
License: MIT
Platform: UNKNOWN
Classifier: Development Status :: 5 - Production/Stable
Classifier: Environment :: Console
Classifier: Intended Audience :: Developers
Classifier: License :: OSI Approved :: MIT License
Classifier: Programming Language :: Python :: 3 :: Only
Classifier: Topic :: Software Development :: Libraries :: Python Modules
Classifier: Topic :: Utilities
Requires-Python: >=3
